{
  "project_info": {
    "project_number": "1034838911860",
    "project_id": "androidcicd-7aca5",
    "storage_bucket": "androidcicd-7aca5.appspot.com"
  },
  "client": [
    {
      "client_info": {
        "mobilesdk_app_id": "1:1034838911860:android:12beaf89a2652219ba1a21",
        "android_client_info": {
          "package_name": "com.example.android"
        }
      },
      "oauth_client": [],
      "api_key": [
        {
          "current_key": "AIzaSyBCcRJzcGDYHaUBi6wEAScBtxHe4E_2kr0"
        }
      ],
      "services": {
        "appinvite_service": {
          "other_platform_oauth_client": []
        }
      }
    }
  ],
  "configuration_version": "1"
}